spark_ai_sdk/__init__.py
spark_ai_sdk/spark_ai.py
spark_ai_sdk-0.0.4.dist-info/METADATA
spark_ai_sdk-0.0.4.dist-info/WHEEL
spark_ai_sdk-0.0.4.dist-info/top_level.txt
spark_ai_sdk-0.0.4.dist-info/RECORD
