Metadata-Version: 2.1
Name: spark-ai-sdk
Version: 0.0.4
Summary: python sdk for XunFei (iFLYTEK) Spark AI
Author: Tlntin
Project-URL: Homepage, https://github.com/Tlntin/spark-ai-sdk
Project-URL: Bug Tracker, https://github.com/Tlntin/spark-ai-sdk/issues
Classifier: Programming Language :: Python :: 3
Classifier: License :: OSI Approved :: Apache Software License
Classifier: Operating System :: OS Independent
Requires-Python: >=3.7
Requires-Dist: websocket-client (>=1.6.1)
